inline_snapshot_phash-0.1.2.dist-info/METADATA
inline_snapshot_phash-0.1.2.dist-info/WHEEL
inline_snapshot_phash-0.1.2.dist-info/entry_points.txt
inline_snapshot_phash/__init__.py
inline_snapshot_phash/_format.py
inline_snapshot_phash/_storage.py
inline_snapshot_phash-0.1.2.dist-info/RECORD
