Metadata-Version: 2.1
Name: inline-snapshot-phash
Version: 0.1.2
Summary: Perceptual hash storage protocol for inline-snapshot
Author-Email: Louis Maddox <louismmx@gmail.com>
License: MIT
Classifier: Development Status :: 3 - Alpha
Classifier: Framework :: Pytest
Classifier: Intended Audience :: Developers
Classifier: Operating System :: OS Independent
Classifier: Topic :: Software Development :: Testing
Classifier: Programming Language :: Python
Classifier: Programming Language :: Python :: 3.8
Classifier: Programming Language :: Python :: 3.9
Classifier: Programming Language :: Python :: 3.10
Classifier: Programming Language :: Python :: 3.11
Classifier: Programming Language :: Python :: 3.12
Classifier: Programming Language :: Python :: 3.13
Classifier: Programming Language :: Python :: 3.14
Classifier: Programming Language :: Python :: Implementation :: CPython
Classifier: Programming Language :: Python :: Implementation :: PyPy
Classifier: License :: OSI Approved :: MIT License
Project-URL: Homepage, https://github.com/lmmx/inline-snapshot-phash
Project-URL: Repository, https://github.com/lmmx/inline-snapshot-phash
Project-URL: Issues, https://github.com/lmmx/inline-snapshot-phash/issues
Requires-Python: >=3.8
Requires-Dist: inline-snapshot[black]>=0.30.1
Requires-Dist: czkawka>=0.1.2
